{"PWgWARNlnGJ71PT0JCMeDg==":"mbr-2000x1190.jpg","OhZfmki3znlefVhpgPHeQQ==":"connected_intelligence_icon_final_files_without_backgground-128x128.jpg","cbclSwuK3GhQyEWAb6uA8g==":"connected_intelligence_logo_final_files_without_backgground-128x128.png","WWx5E36ct3JhLymw3VEpEA==":"unspecified-128x128.png","ECz3TAmyXpoVDMfov/JBPw==":"ed-vincent-600x600.png","HOtXHD9R/P42tviCnCUYfg==":"chris-bryant-600x600.png","0BM2kkT+ie/npCXolfacrg==":"jess-marcus-600x600.png","i74lXmKJqkAJVITkqBS02g==":"mbr-2000x1332.jpg","n5W3ppP8m1y4gTDKefi9/Q==":"mbr-2000x1333.jpg","Hn2RMO7hSLzfE+/XUKGPSw==":"mbr-2000x1364.jpg","quF1zzxomYS2dtNbQRipZA==":"mbr-2000x1334.jpg","y3MNuuh28lbx/hB8i9B4ow==":"mbr-2000x2589.jpg","ArBEviI0i5YMRV1vT3LkrQ==":"mbr-1-2000x1333.jpg","WQnkFm/xV7Bh5HFC8keJ1Q==":"mbr-2-2000x1333.jpg","gKB8VswyGf2NoRcQCdYFYA==":"roi-logo-top-menu-x-2000x638.png","THNKb4GMF2rpqgknWNcnwA==":"movie_tickets_logo-2000x800.png","u8uOcM6aet7wmbSce9yV8g==":"predict-logo-email-footer2-2000x1800.png","06vOy3nUbc7igfRW01687A==":"logo_rubicon_project_2014_official-2000x598.png","KO6MqY6Y984dGaOmZF7Klw==":"openx-logo-2000x1500.png","ZgUTXV/VUy25SeickyyW2Q==":"double-click-2000x487.png","CHTFYH7uH17tJDcUT6TQiA==":"pubmatic-squarelogo-2000x2000.png","vNFQcqHMDjoPvUyoMsDkZQ==":"redlogomd-2000x570.png","kAEvvxXoMkcw0UpqrWp8eA==":"sv_media_logo-2000x1088.png","oaOORChTofE3YImN0Cfihw==":"mbr-1400x934.jpg","p2Z9Oqa0CbYWbff36REEFw==":"mbr-1400x708.jpg","Ce6HVfPEBKzhxdHr9U74ZQ==":"mbr-1400x933.jpg","r2nhtsdC95a0b44Oy3tDPg==":"mbr-1-2000x1190.jpg","Zact0N7ED1qQhVA60MfhIw==":"connected_intelligence_icon_final_files_white-128x128.jpg","cZt2vHVVVijt8Jc7SHhv/Q==":"connected_intelligence_logo_final_files_white_background-178x128.jpg","TaqBQS7elYmD84IA5xzdxA==":"connected_intelligence_logo_final_files_white_background-128x128.png","lPclTmc/TsNvvF5os9hgWQ==":"ci_logo-178x128.png","Wguy3WDaWD9M11kEotd+oQ==":"ci_logo-1-178x128.png","YuEeo4kcm4kCurseJfiBgw==":"ed-vincent-600x600%20copy-600x600.png","115spvtLPY4qwsnzlUSQ/g==":"mbr-1-2000x1334.jpg","2+oowSng8EHeM9F7ep+q9Q==":"screen%20shot%202017-06-05%20at%2010-2000x785.jpg","n1E+DqTfDQR0yHDQnAMFHQ==":"mbr-3-2000x1333.jpg","U8MzI20hp2+Mr95PchjW2Q==":"mbr-4-2000x1333.jpg","Mx3ta8uudXKTUWGX2UYdQQ==":"sv_media_logo_200x109-2000x1090.png","zxX3lYj7TGDs75H5Ynq5Cw==":"movie_tickets_logo_200x109-2000x1090.png","QhXZjGvIgz9tqGAq7Ah/XA==":"logo_rubicon_project_200x109copy-2000x1090.png","xfIjvJEjHwOv24f334ip4g==":"openx-logo-200x109%20copy-2000x1090.png","B51bVxwQcVLbWtNf2vdbFQ==":"roi-logo-top-200x109%20copy-2000x1090.png","2kQZDdCyjuz2jGIZMv3XBg==":"media_math_200x109-2000x1090.png","T2axPHntpSh6PgdYA1J5Ew==":"predict-logo-2000x1090.png","IxbGChRIDB+rOc5TRcBMvQ==":"double-click%20_200x109copy-2000x1090.png","gOVkmz3XUIKBsdt/KUadzQ==":"pubmatic-squarelogo-2000x1090.png","NdQfMV1W+c2HZBKkedJ1/g==":"chris-bryant-1400x1400.png","p+j4wQY1cL9yNqPae8mBDg==":"jess-marcus-1400x1400.png","ts4rbM/vLBLX+/Sf0llWWA==":"mbr-2-2000x1334.jpg","DOeMBBbpgQpg9RYKztG3ow==":"screen%20shot%202017-06-07%20at%2011-1400x1547.png","6wmU8jcjiuzPQvBLKqdBcQ==":"mbr-5-2000x1333.jpg","seqbxsjbFnf1xfZl72rs0Q==":"mbr-2000x1125.jpg","H3WhQNonZX2oLzAX4cFClQ==":"mbr-2000x1600.jpg","C5yXjIy+H/gTSVzLhLmVIA==":"mbr-2000x1500.jpg","wdciPDQ+HRICwok4lihjKw==":"mbr-6-2000x1333.jpg","cYxXUhjwQX24ypM+2x+1oQ==":"screen%20shot%202017-06-05%20at%2010-2000x785.png","/tWnkuHTDf8SL65tfH4cag==":"mbr-2000x1328.jpg","h/Bc0YmLOi3T7T9IeA7ULA==":"mbr-7-2000x1333.jpg","dHKdHaHkS6amjYfVYK2ELg==":"mbr-8-2000x1333.jpg","I3adQTds2pJuQOUUzVSQhQ==":"screen%20shot%202017-06-14%20at%201-2000x1098.png","qmciOmCkBZMsg6NXAf58FA==":"1-2000x1126.jpg","PgiYxzqYTpKc7Ru0Ocm9vw==":"mbr-2000x1321.jpg","gr9qcNoa9fSiCnyxotiPoQ==":"sv-media-logo-800x435.png","oUM63CYil3N/cJGHNEeGPw==":"imgres-2000x1085.png","8iYUZCxnZVILrA6cUoGmXg==":"mbr-3-2000x1334.jpg","JDqOUV0/pcxCo+/3gbG6kA==":"movie-tickets-logo-800x436.png","HCYZCIJOACydA/PgXTRb2w==":"movie-tickets-logo-800x320.png","Qk5aa7VTeC6OmPhGvZi1PA==":"sv_white-221x120.png","+0aK+zdNZzZJfiGvjw3Kmw==":"mt_white-2000x800.png","fNUhYAQ9LizJ9EVV6CGrOA==":"a&e_white-206x140.png","D3JIY2uBJh8Uxul+haI7wQ==":"mt_white-1-2000x800.png","DgkfJUzC2NDf0VMRE8h5Jw==":"mt_white-800x320.png","jzKb8198W/1kjHpSj6ZXsA==":"logos-movietickets-400x400.png","mwVy9nYodQHYAJTz/d4Tqw==":"a&e_white%20copy-206x140.png","7zCfosg4/0nz+bplAQRwHg==":"a&e_white%20copy-206x140.png","8K8XJv80UyLNOJ3HFdzTKQ==":"a-e-networks%20copy-1024x1024.png","N+itnRZjqtxDw8tBPZc3YQ==":"a&e-206x140.png","H+iOLjnM5ulZrfq5SQx8vw==":"a_e-216x166.png","V0GsAwyCdmBbhj0e3hMRmw==":"pv_logo_large-1-128x25.png","JNkvJm6pUYID+QNjz/s0QQ==":"pv_logo_large-128x25.png","a93pAWnDd1jUw+GeebnmuA==":"connected_intelligence_icon_final_files_white-128x128.png","rPIG5LY4sQ9QnVwJXRhqUw==":"connected_intelligence_icon_final_files_white-1-128x128.png","50UShXlgqE26pJNLcGhURQ==":"ci-127x128.png","2xonjcegHQ0luUWZPsbADg==":"connected_intelligence_logo_final_files_horizontal-128x128.png","MM1xPCLCJm894Z6UDfmK5g==":"connected_intelligence_logo_final_files_horizontal%20(1)-214x128.png","AFPp2L0UnhyHMGORlh2bYQ==":"connected_intelligence_logo_final_files_horizontal%20(1)-214x128.png","s8ijq0T2bmXYHXkmP1Q9cQ==":"connected_intelligence_logo_final_files_horizontal%20(1)-214x128.png","5TMPCVnZWaXovjpZqrIXNA==":"connected_intelligence_logo_final_files_horizontal%20(1)-499x128.png","grvjFV6bXFHFTn90mMBtYQ==":"slide1-720x540.png","6UaekzzRwGzrlUzwX8T97A==":"mbr-600x400.jpg","WEWzoUngETTs+ruEbbzoAA==":"movie-tickets-logo-2000x800.png","kO9MiJvgxWa/+bBmlOZg4w==":"download-144x62.png","+R/4FcvkemZo+dDl1zsDIA==":"sv_media_logo-180x100.png","mpO/9yb/CJM/ZlR7IOAkjw==":"connected_intelligence_logo_final_files_horizontal%20(1)-265x64.png","YUxm0bT0709nr40kIm/ZKQ==":"mbr-1400x997.jpg","CTV8hJgC0Jh2FZ99b2HW0Q==":"mbr-1623x1080.jpg","ujvGmMLGJHomtJxbznu87Q==":"pv_logo_large-265x53.png","5XE9wWyloYgbegrlnspX/Q==":"mbr-2000x1123.jpg","mq9tHdaaEkt/JvLhNw39rA==":"mbr-4-2000x1334.jpg","LZ6lO8cctXPxGDcyp1imQw==":"mbr-2000x1324.jpg","9vbingsH0x0Auqq8tPFmYA==":"mbr-1-2000x1324.jpg","P5XQGkbwO1eAR/0jIqWlbg==":"download-216x93.png","6OE4R5lP0X5hdY6/e4fJjA==":"a-e-networks-216x216.png","ShOzVxb9wYLyUHPIvhE3dw==":"a-e-networks-200x123.png","qKAyAzkVb3+EefBhirVSVA==":"download-207x84.png","LIeiMy1x9BwA7KF8V/zmEQ==":"download-288x124.png","RNRzCJG/7IcwqILVXPkZfw==":"sv_media_logo-450x251.png","Y+VkW6WKT1XC/WEzkDXKFQ==":"sv_media_logo-300x167.png","6CzJPKQSL6yXNSXofPColg==":"sv_media_logo-240x134.png","pffl+vqdw1v7xKU0S59atA==":"mbr-2000x1443.jpg","sThhIhaqKwXYZ4Tsj7GUfg==":"mbr-9-2000x1333.jpg","lrhz+SL//JEYI0EzvZDe+w==":"mbr-10-2000x1333.jpg","7MDXJjerYhRYY9TfmcGN1g==":"mbr-5-2000x1334.jpg","9+0gzEEYE50NOn35Tsnfaw==":"mbr-2000x1325.jpg","YhT9i1r1hDkXRWtQf/7fPA==":"cinema-2000x1332.png","doAhziAe5F4S6+47cMn5Dw==":"influencer-2000x1332.png","jr2Z8fNFLP4A5z5o2/OceA==":"influencer-1-2000x1332.png","+VE60BmawXjlLNmTbKt9kQ==":"influencer-2-2000x1332.png","4BPjfjJl2HOae4l8XgZcew==":"svod-2000x1334.png","TR2iHSdJxtC6KkwwlE8PzQ==":"svod-1-2000x1334.png","PWJzeE9RuzmmqO14PyFYiA==":"svod-2-2000x1334.png","KplfSn5ZE5p12LW6A0qUCg==":"svod-3-2000x1334.png","u4jDfsRpdVughji46+fXqg==":"svod-4-2000x1334.png","KIWfXRM0LAqJm6Q+dKQ1pw==":"svod-5-2000x1334.png","lv49vSJiNMENi/PuV9lB0Q==":"fintech-2000x1325.png","C+bvbMqIF76q4AnPyCKdJg==":"fintech-1-2000x1325.png","9zSTASf3k2EgaIRkxMnDBw==":"svod2-2000x1334.png","9KL6Y+/FypDZ39v4xF7+xA==":"svod2-1-2000x1334.png","LEY03jWoIzKQfYGKRBrwQw==":"slide1-2000x1500.png","+4YDW21nlLria4WGnlS1cA==":"slide1-1400x1050.png","z1/uYSZcXExAeVRQsjQnkQ==":"mbr-11-2000x1333.jpg","wxIH6RjPFL+XA/rkFVH/zQ==":"mbr-12-2000x1333.jpg","4nCjZHZDrV3qpJrfa0niTQ==":"svod-800x533.png","zGciDehZAOk7pYwXNy3MbA==":"connected_intelligence_logo_final_files_horizontal-1-128x128.png","0A5FwAY4CMS2VVbeQHJv0Q==":"connected_intelligence_logo_final_files_horizontal-373x128.png"}